dpmkit/__init__.py
dpmkit/__main__.py
dpmkit/util.py
dpmkit-0.0.1.dist-info/LICENSE
dpmkit-0.0.1.dist-info/METADATA
dpmkit-0.0.1.dist-info/WHEEL
dpmkit-0.0.1.dist-info/entry_points.txt
dpmkit-0.0.1.dist-info/top_level.txt
dpmkit-0.0.1.dist-info/RECORD
