Metadata-Version: 2.1
Name: dpmkit
Version: 0.0.1
Summary: A simple tool for creating DPMKs.
Author-email: hexaheximal <hexaheximal@proton.me>, JustSoup321 <brandonboese@protonmail.com>
License: GNU GENERAL PUBLIC LICENSE
Project-URL: Homepage, https://github.com/lowendlibre/dpmkit
Keywords: linux,kernel,postmarketos
Classifier: License :: OSI Approved :: GNU General Public License (GPL)
Classifier: Programming Language :: Python
Classifier: Programming Language :: Python :: 3
Requires-Python: >=3.7
License-File: LICENSE
